fast_puc/__init__.py
fast_puc/fast_puc.py
fast_puc-0.2.1.dist-info/METADATA
fast_puc-0.2.1.dist-info/WHEEL
fast_puc-0.2.1.dist-info/licenses/LICENSE
fast_puc-0.2.1.dist-info/RECORD
