Metadata-Version: 2.4
Name: fast_puc
Version: 0.2.1
Summary: FaSt_PUC converts numbers to strings with appropriate unit prefix.
Project-URL: Homepage, https://www.fast-apps.de
Author-email: Fabian Stutzki <fast@fast-apps.de>
License: MIT
License-File: LICENSE
Keywords: unit
Classifier: License :: OSI Approved :: MIT License
Classifier: Operating System :: OS Independent
Classifier: Programming Language :: Python :: 3
Requires-Python: >=3.9
Requires-Dist: numpy>=1.2.0
Requires-Dist: pytest>=8.0.0
